bblocks/data_importers/__init__.py
bblocks/data_importers/baci/baci.py
bblocks/data_importers/baci/data_manager.py
bblocks/data_importers/config.py
bblocks/data_importers/data_validators.py
bblocks/data_importers/imf/__init__.py
bblocks/data_importers/imf/dsa.py
bblocks/data_importers/imf/weo.py
bblocks/data_importers/protocols.py
bblocks/data_importers/unaids/__init__.py
bblocks/data_importers/unaids/unaids.py
bblocks/data_importers/undp/__init__.py
bblocks/data_importers/undp/hdi.py
bblocks/data_importers/utilities.py
bblocks/data_importers/wfp/__init__.py
bblocks/data_importers/wfp/wfp.py
bblocks/data_importers/who/__init__.py
bblocks/data_importers/who/ghed.py
bblocks/data_importers/world_bank/__init__.py
bblocks/data_importers/world_bank/international_debt_statistics.py
bblocks/data_importers/world_bank/world_bank.py
bblocks_data_importers-0.5.0.dist-info/METADATA
bblocks_data_importers-0.5.0.dist-info/WHEEL
bblocks_data_importers-0.5.0.dist-info/licenses/LICENSE
bblocks_data_importers-0.5.0.dist-info/RECORD
