Metadata-Version: 2.4
Name: bblocks-data-importers
Version: 0.5.0
Summary: Tools to import data from different sources. Part of the bblocks project.
License: MIT
License-File: LICENSE
Author: ONE Campaign
Requires-Python: >=3.11,<4.0
Classifier: License :: OSI Approved :: MIT License
Classifier: Programming Language :: Python :: 3
Classifier: Programming Language :: Python :: 3.11
Classifier: Programming Language :: Python :: 3.12
Classifier: Programming Language :: Python :: 3.13
Classifier: Programming Language :: Python :: 3.14
Requires-Dist: bblocks-places (>=0.0.4)
Requires-Dist: camelot-py (>=1.0.9)
Requires-Dist: country-converter (>=1.3.1,<2.0.0)
Requires-Dist: diskcache (>=5.6.3,<6.0.0)
Requires-Dist: httpx (>=0.28.1,<0.29.0)
Requires-Dist: imf-reader (>=1.3.0,<2.0.0)
Requires-Dist: openpyxl (>=3.1.5,<4.0.0)
Requires-Dist: pandas (>=2.2.3,<3.0.0)
Requires-Dist: pyarrow (>=20.0.0,<21.0.0)
Requires-Dist: wbgapi (>=1.0.12,<2.0.0)
Project-URL: Documentation, https://docs.one.org/tools/bblocks/data-importers/
Project-URL: Homepage, https://docs.one.org/tools/bblocks/data-importers/
Project-URL: Repository, https://github.com/ONEcampaign/bblocks_data_importers
